genpeds/__init__.py
genpeds/cfg.json
genpeds/cleaners.py
genpeds/core.py
genpeds/downloader.py
genpeds-1.2.1.dist-info/licenses/LICENSE.md
genpeds-1.2.1.dist-info/METADATA
genpeds-1.2.1.dist-info/WHEEL
genpeds-1.2.1.dist-info/top_level.txt
genpeds-1.2.1.dist-info/RECORD
