Metadata-Version: 2.4
Name: genpeds
Version: 1.2.1
Summary: Work with NCES IPEDS data: from admissions to graduation
Author-email: Ravan Hawrami <ravanhawrami@gmail.com>
License-Expression: MIT
Classifier: Programming Language :: Python :: 3
Classifier: Operating System :: OS Independent
Requires-Python: >=3.9
License-File: LICENSE.md
Requires-Dist: pandas
Requires-Dist: numpy
Requires-Dist: openpyxl
Requires-Dist: xlrd
Requires-Dist: requests
Requires-Dist: bs4
Requires-Dist: us
Dynamic: license-file
